labinstruments/__init__.py
labinstruments/agilent.py
labinstruments/hittite.py
labinstruments/keithley.py
labinstruments/microlambda.py
labinstruments/siglent.py
RxLab_Instruments-0.0.2.dist-info/LICENSE.md
RxLab_Instruments-0.0.2.dist-info/METADATA
RxLab_Instruments-0.0.2.dist-info/WHEEL
RxLab_Instruments-0.0.2.dist-info/top_level.txt
RxLab_Instruments-0.0.2.dist-info/RECORD
